panoptisch/__init__.py
panoptisch/imports.py
panoptisch/lib_resolver.py
panoptisch/sandbox.py
panoptisch/scanner.py
panoptisch/util.py
panoptisch/visitor.py
panoptisch-0.1.6.dist-info/entry_points.txt
panoptisch-0.1.6.dist-info/LICENSE
panoptisch-0.1.6.dist-info/WHEEL
panoptisch-0.1.6.dist-info/METADATA
panoptisch-0.1.6.dist-info/RECORD
