Metadata-Version: 2.1
Name: panoptisch
Version: 0.1.6
Summary: A recursive Python dependency scanner.
Home-page: https://github.com/R9295/panoptisch
License: GPL-3.0
Keywords: Dependency Scanner,Security,Supply Chain,Tool
Author: aarnav
Author-email: aarnavbos@gmail.com
Requires-Python: >=3.10,<4.0
Classifier: License :: OSI Approved :: GNU General Public License v3 (GPLv3)
Classifier: Operating System :: OS Independent
Classifier: Programming Language :: Python :: 3
Classifier: Programming Language :: Python :: 3.10
Classifier: Programming Language :: Python :: 3.11
Classifier: Topic :: Security
Requires-Dist: anytree (>=2.8.0,<3.0.0)
Project-URL: Documentation, https://github.com/R9295/panoptisch
Project-URL: Repository, https://github.com/R9295/panoptisch
